setup.cfg
setup.py
djes_file_fields/__init__.py
djes_file_fields/fields.py
djes_file_fields.egg-info/PKG-INFO
djes_file_fields.egg-info/SOURCES.txt
djes_file_fields.egg-info/dependency_links.txt
djes_file_fields.egg-info/requires.txt
djes_file_fields.egg-info/top_level.txt