Metadata-Version: 1.0
Name: djes-file-fields
Version: 1.0.4
Summary: Adding sensible field mappers for django field type fields
Home-page: https://github.com/vforgione/djes-file-fields
Author: Vince Forgione
Author-email: v.forgione@gmail.com
License: MIT
Platform: UNKNOWN
